{
    "GameName": "Dark Souls III",
    "GuidePSNP": "4281-dark-souls-iii-trophy-guide",
    "GuidePS3T": "https://www.playstationtrophies.org/game/dark-souls-3/guide/",
    "GuidePS3I": "",
    "GuidePyx": "https://www.powerpyx.com/guides/dark-souls-3-trophy-guide.html",
    "GuideKnoef": "",
    "GuideYoutube": "00000000000",
    "GuideDex": "",
    "GuideTrophiesDE": "https://www.trophies.de/forum/thema/132338-troph%C3%A4en-leitfaden-dark-souls%E2%84%A2-iii",
    "GuideCust": "",
    "GuideCustLabel": "",
    "GameImg": "https://image.api.playstation.com/gs2-sec/appkgo/prod/CUSA03365_00/2/i_1bf8d3317ff642710196c85c859320f0a9345e3c65a9132d588239fab877d81a/i/icon0.png",
    "UnobtainableTrophies": "",
    "GameID": "CUSA03388",
    "Desc": "The DARK SOULS III Deluxe Edition includes the full game & the Season Pass. First DLC coming Fall 2016. DARK SOULS III pushes the boundaries with the latest chapter in the series. Journey once more into a world filled with daunting, colossal enemies and environments. Players will be immersed into a world of epic atmosphere and darkness through faster gameplay and amplified combat intensity. With the new skills attacks, deliver powerful attacks to break through enemy defense weapons equipped with unique skills. Expand your experience with the Season Pass content featuring new maps, bosses, enemies and additional weapon and armor sets. Embrace The Darkness!",
    "Img": "https://image.api.playstation.com/cdn/UP0700/CUSA03388_00/Fg2otuFMeKjhnXG2QLUrwKqrMNvsC0n9.png",
    "CoverArt": "https://image.api.playstation.com/vulcan/img/rnd/202010/0823/nwAKSQRMXqURmgOYHaxickuk.png",
    "LogoImg": "https://image.api.playstation.com/vulcan/img/rnd/202010/0822/0p6wO8PkVsDjPntPBcsHSkOA.png",
    "Screenshot1": "https://image.api.playstation.com/vulcan/img/rnd/202010/0823/VrGmJUyUWqMBVhhvGowb6hXq.jpg",
    "Screenshot2": "https://image.api.playstation.com/vulcan/img/rnd/202010/0823/7hosVKSR2b7VPVOtfp7rDTZ3.jpg",
    "Screenshot3": "https://image.api.playstation.com/vulcan/img/rnd/202010/0823/RHgdm97GVu1FBiBL9Lsxxe6v.jpg",
    "Screenshot4": "https://image.api.playstation.com/vulcan/img/rnd/202010/0823/P2zlJtnaG1wfRmg6fTiSAusG.jpg",
    "Screenshot5": "https://image.api.playstation.com/vulcan/img/rnd/202010/0823/VTGFPgDF4Z1FvHAp5LFTxTm6.jpg",
    "Screenshot6": "https://image.api.playstation.com/vulcan/img/rnd/202010/0823/MjSef2xM8l36gPG0yZ9G5F7J.jpg",
    "Screenshot7": "https://image.api.playstation.com/vulcan/img/rnd/202010/0823/BQNnUfmvk097R1qdHzwjSBhf.jpg",
    "Screenshot8": "https://image.api.playstation.com/vulcan/img/rnd/202010/0823/0nUcgegErR7Du10mDUZ798bR.jpg",
    "Screenshot9": "https://image.api.playstation.com/vulcan/img/rnd/202010/0823/FYUOrf3v8hMW1l4gWZy2Llba.jpg",
    "PreviewVideo": "",
    "Publisher": "BANDAI NAMCO Entertainment America Inc.",
    "Developer": "FromSoftware",
    "IsPS4": "1",
    "IsPS5": "0",
    "IsVR": "0",
    "IsMove": "0",
    "VitaCB": "0",
    "PS4Size": "18244304896",
    "PS5Size": "0",
    "OnlinePlay": "1",
    "OfflinePlayers": "1",
    "OnlinePlayers": "6",
    "PSPlusNeeded": "0",
    "IsDLC": "0",
    "VoiceLang": "",
    "SubtitleLang": "",
    "OpenCriticID": "1520",
    "MetacriticURL": "",
    "GenreRPG": "1",
    "GenreAction": "1",
    "GenreAdventure": "1",
    "GenreTPS": "0",
    "GenreFPS": "0",
    "GenreMMO": "0",
    "GenrePlatformer": "0",
    "GenreFighting": "0",
    "GenreSimulation": "0",
    "GenreArcade": "0",
    "GenreStrategy": "0",
    "GenreSports": "0",
    "GenrePuzzle": "0",
    "GenreMusic": "0",
    "GenreRacing": "0",
    "GenreHorror": "0",
    "GenreIntStory": "0",
    "OldDifficulty": "6",
    "Region": "US",
    "BasePrice": "8499",
    "PlusPrice": "8499",
    "SalePrice": "8499",
    "LowestEverPrice": "8388607",
    "LowestEverPlusPrice": "8388607",
    "DiscPerc": "50",
    "ReleaseDate": "2016-04-12",
    "LastDiscounted": "2022-12-21 12:43:47",
    "DiscountedUntil": "2023-01-07 07:59:00",
    "PSPExPremUntil": "2001-00-00 01:00:00",
    "PSPExtra": "0",
    "PSPPremium": "0",
    "PSNID": "UP0700-CUSA03388_00-DARKSOULS3DELUXE",
    "ProductName": "Dark Souls III - Deluxe Edition",
    "PPID": "7704",
    "TrophyListURL": "https://psnprofiles.com/trophies/4477-dark-souls-iii",
    "Rating": "ESRB Mature",
    "RatingDesc": "[\"Violencia\",\"Sangre\",\"Interacciones online no clasificadas por la ESRB\"]",
    "IsDemoOrSoundtrack": "0",
    "Bronze": "26",
    "Silver": "13",
    "Gold": "3",
    "Platinum": "1",
    "Difficulty": "6",
    "HoursLow": 75,
    "HoursHigh": 100,
    "formattedBasePrice": "$84.99",
    "formattedSalePrice": "$84.99",
    "formattedPlusPrice": "$84.99",
    "PSStoreURL": "https://store.playstation.com/en-us/product/UP0700-CUSA03388_00-DARKSOULS3DELUXE",
    "PlatPricesURL": "https://platprices.com/en-us/game/7704-dark-souls-iii-deluxe-edition",
    "error": 0,
    "errorDesc": "",
    "apiLimit": "500",
    "apiUsage": "5"
}
